[
  {
  "id": "base-chain-pause",
  "pausedFromChains": [8453],
  "pausedToChains": [8453],
  "startTime": "2024-04-12T17:41:00Z",
  "endTime": null,
  "bannerStartTime": "2024-04-12T04:40:00Z",
  "bannerEndTime": null,
  "warningMessage": "Base bridging is paused until maintenance is complete.",
  "bannerMessage": "Base bridging is paused until maintenance is complete.",
  "progressBarMessage": "Base maintenance in progress",
  "disableBanner": false,
  "disableWarning": false,
  "disableCountdown": false
}
]
