{
  "chains": {
    "arbitrum": "--auto-gas-1559",
    "aurora": "--legacy --slow",
    "base": "--auto-gas-1559",
    "blast": "--auto-gas-1559",
    "boba": "--legacy --skip-simulation --slow",
    "canto": "--legacy --slow",
    "cronos": "--slow",
    "dfk": "--slow",
    "dogechain": "--legacy --slow",
    "harmony": "--legacy --slow",
    "klaytn": "--skip-simulation",
    "mainnet": "--auto-gas-1559",
    "metis": "--legacy",
    "moonbeam": "--skip-simulation --slow",
    "moonriver": "--skip-simulation --slow",
    "optimism": "--auto-gas-1559",
    "polygon": "--slow",
    "scroll": "--legacy"
  },
  "deployConfigs": "configs",
  "deployments": "deployments",
  "forgeArtifacts": "out",
  "freshDeployments": ".deployments"
}
